[
  {
    "calculator": true,
    "focus": "default",
    "paperAccess": {
      "papers/paper3.txt": true,
      "papers/paper1.txt": false,
      "papers/paper2.txt": false
    }
  },
  {
    "calculator": true,
    "focus": "default",
    "paperAccess": {
      "papers/paper3.txt": false,
      "papers/paper1.txt": true,
      "papers/paper2.txt": false
    }
  },
  {
    "calculator": true,
    "focus": "default",
    "paperAccess": {
      "papers/paper3.txt": false,
      "papers/paper1.txt": false,
      "papers/paper2.txt": true
    }
  },
  {
    "calculator": true,
    "focus": "default",
    "paperAccess": {
      "papers/paper3.txt": false,
      "papers/paper1.txt": false,
      "papers/paper2.txt": false
    }
  }
]